{
  "event_element": [
    {
      "event_sentence": "2010年12月17日晚，湖南宁乡县横市镇铁冲村发生一起运输烟花鞭炮引线的运输车的爆炸事故。",
      "event_graph": [
        {
          "child_event_id": "e01",
          "trigger": "发生",
          "trigger_object": "爆炸事故",
          "object_attri": "一起运输烟花鞭炮引线的运输车",
          "time": "2010年12月17日晚",
          "time_align": "2010-12-17-XX-XX",
          "location": "湖南宁乡县横市镇铁冲村",
          "organization": "",
          "person": "",
          "subject_attri": "",
          "trigger_subject": "湖南宁乡县横市镇铁冲村"
        }
      ]
    },
    {
      "event_sentence": "根据事故处置指挥部19日晚10时许发布最新消息，经过公安部门调查和认定，此次事故导致12人遇难（其中9人身份已确认，3人身份正在确认），9人受伤，另有2人失踪。",
      "event_graph": [
        {
          "child_event_id": "e02",
          "trigger": "发布",
          "trigger_object": "消息",
          "object_attri": "最新",
          "time": "19日晚10时",
          "time_align": "2010-12-19-22-00",
          "location": "湖南宁乡县横市镇铁冲村",
          "organization": "",
          "person": "",
          "subject_attri": "",
          "trigger_subject": "事故处置指挥部"
        },
        {
          "child_event_id": "e03",
          "trigger": "调查",
          "trigger_object": "",
          "object_attri": "",
          "time": "19日晚10时",
          "time_align": "2010-12-19-22-00",
          "location": "湖南宁乡县横市镇铁冲村",
          "organization": "",
          "person": "",
          "subject_attri": "",
          "trigger_subject": "公安部门"
        },
        {
          "child_event_id": "e04",
          "trigger": "认定",
          "trigger_object": "",
          "object_attri": "",
          "time": "19日晚10时",
          "time_align": "2010-12-19-22-00",
          "location": "湖南宁乡县横市镇铁冲村",
          "organization": "",
          "person": "",
          "subject_attri": "",
          "trigger_subject": "公安部门"
        },
        {
          "child_event_id": "e05",
          "trigger": "导致",
          "trigger_object": "遇难",
          "object_attri": "12人、其中9人身份已确认，3人身份正在确认",
          "time": "19日晚10时",
          "time_align": "2010-12-19-22-00",
          "location": "湖南宁乡县横市镇铁冲村",
          "organization": "",
          "person": "",
          "subject_attri": "此次",
          "trigger_subject": "事故"
        },
        {
          "child_event_id": "e06",
          "trigger": "导致",
          "trigger_object": "受伤",
          "object_attri": "9人",
          "time": "19日晚10时",
          "time_align": "2010-12-19-22-00",
          "location": "湖南宁乡县横市镇铁冲村",
          "organization": "",
          "person": "",
          "subject_attri": "此次",
          "trigger_subject": "事故"
        },
        {
          "child_event_id": "e07",
          "trigger": "导致",
          "trigger_object": "失踪",
          "object_attri": "2人",
          "time": "19日晚10时",
          "time_align": "2010-12-19-22-00",
          "location": "湖南宁乡县横市镇铁冲村",
          "organization": "",
          "person": "",
          "subject_attri": "此次",
          "trigger_subject": "事故"
        }
      ]
    },
    {
      "event_sentence": "目前事故正在进一步调查中。",
      "event_graph": [
        {
          "child_event_id": "e08",
          "trigger": "被-调查",
          "trigger_object": "",
          "object_attri": "",
          "time": "目前",
          "time_align": "",
          "location": "",
          "organization": "",
          "person": "",
          "subject_attri": "",
          "trigger_subject": "事故"
        }
      ]
    }
  ],
  "event_relation": {
    "e01": {
      "e02": "顺承关系",
      "e05": "因果关系",
      "e06": "因果关系",
      "e07": "因果关系"
    },
    "e02": {
      "e03": "顺承关系"
    },
    "e03": {
      "e04": "并列关系",
      "e05": "顺承关系"
    },
    "e04": {
      "e05": "顺承关系"
    },
    "e05": {
      "e06": "并列关系",
      "e07": "并列关系",
      "e08": "顺承关系"
    },
    "e06": {
      "e07": "并列关系",
      "e08": "顺承关系"
    },
    "e07": {
      "e08": "顺承关系"
    }
  }
}